py_json_config/__init__.py
py_json_config-0.1.4.dist-info/METADATA
py_json_config-0.1.4.dist-info/WHEEL
py_json_config-0.1.4.dist-info/RECORD
