Metadata-Version: 2.1
Name: py-json-config
Version: 0.1.4
Summary: JSONConfig was created to use .json files as configs
Author: Enveloss
Requires-Python: >3.5
Classifier: Programming Language :: Python :: 3
Classifier: Programming Language :: Python :: 3.6
Classifier: Programming Language :: Python :: 3.7
Classifier: Programming Language :: Python :: 3.8
Classifier: Programming Language :: Python :: 3.9
Classifier: Programming Language :: Python :: 3.10
Classifier: Programming Language :: Python :: 3.11
